{"_id":{"$oid":"63452ade10ab555e6021a37d"},"id":{"$numberInt":"1"},"problem":{"$numberInt":"10"},"description":"Solved by using React router","userId":{"$numberInt":"1"}}
{"_id":{"$oid":"63452ade10ab555e6021a37e"},"id":{"$numberInt":"2"},"problem":{"$numberInt":"50"},"description":"Solved by using Node JS","userId":{"$numberInt":"2"}}
{"_id":{"$oid":"63452ade10ab555e6021a37f"},"id":{"$numberInt":"3"},"problem":{"$numberInt":"20"},"description":"Solved by using React Formik","userId":{"$numberInt":"3"}}
{"_id":{"$oid":"63452ade10ab555e6021a380"},"id":{"$numberInt":"4"},"problem":{"$numberInt":"30"},"description":"Solved by using React","userId":{"$numberInt":"4"}}
{"_id":{"$oid":"63452ade10ab555e6021a381"},"id":{"$numberInt":"5"},"problem":{"$numberInt":"90"},"description":"Solved by using React ES5 and ES6","userId":{"$numberInt":"5"}}
{"_id":{"$oid":"63452ade10ab555e6021a382"},"id":{"$numberInt":"6"},"problem":{"$numberInt":"40"},"description":"Solved by using React Components","userId":{"$numberInt":"6"}}
{"_id":{"$oid":"63452ade10ab555e6021a383"},"id":{"$numberInt":"7"},"problem":{"$numberInt":"80"},"description":"Solved by using Javascript Async and Await","userId":{"$numberInt":"7"}}
{"_id":{"$oid":"63452ade10ab555e6021a384"},"id":{"$numberInt":"8"},"problem":{"$numberInt":"70"},"description":"Solved by using Mysql Introduction","userId":{"$numberInt":"8"}}
{"_id":{"$oid":"63452ade10ab555e6021a385"},"id":{"$numberInt":"9"},"problem":{"$numberInt":"60"},"description":"Solved by using Javascript Callback Functions","userId":{"$numberInt":"9"}}
{"_id":{"$oid":"63452ade10ab555e6021a386"},"id":{"$numberInt":"10"},"problem":{"$numberInt":"120"},"description":"Solved by using MongoDB","userId":{"$numberInt":"10"}}
{"_id":{"$oid":"63452ade10ab555e6021a387"},"id":{"$numberInt":"11"},"problem":{"$numberInt":"150"},"description":"Solved by using React DOM","userId":{"$numberInt":"11"}}
{"_id":{"$oid":"63452ade10ab555e6021a388"},"id":{"$numberInt":"12"},"problem":{"$numberInt":"200"},"description":"Solved by using Javascript Promises","userId":{"$numberInt":"12"}}
{"_id":{"$oid":"63452ade10ab555e6021a389"},"id":{"$numberInt":"13"},"problem":{"$numberInt":"130"},"description":"Solved by using React Context API","userId":{"$numberInt":"13"}}
{"_id":{"$oid":"63452ade10ab555e6021a38a"},"id":{"$numberInt":"14"},"problem":{"$numberInt":"160"},"description":"Solved by using Javascript Async and Await","userId":{"$numberInt":"14"}}
{"_id":{"$oid":"63452ade10ab555e6021a38b"},"id":{"$numberInt":"15"},"problem":{"$numberInt":"100"},"description":"Solved by using Javascript Functions","userId":{"$numberInt":"15"}}
{"_id":{"$oid":"63452ade10ab555e6021a38c"},"id":{"$numberInt":"16"},"problem":{"$numberInt":"210"},"description":"Solved by using Javascript","userId":{"$numberInt":"16"}}
{"_id":{"$oid":"63452ade10ab555e6021a38d"},"id":{"$numberInt":"17"},"problem":{"$numberInt":"300"},"description":"Solved by using React Hooks and States","userId":{"$numberInt":"17"}}
{"_id":{"$oid":"63452ade10ab555e6021a38e"},"id":{"$numberInt":"18"},"problem":{"$numberInt":"110"},"description":"Solved by using React Components","userId":{"$numberInt":"18"}}
{"_id":{"$oid":"63452ade10ab555e6021a38f"},"id":{"$numberInt":"19"},"problem":{"$numberInt":"170"},"description":"Solved by using Javascript Async Programming","userId":{"$numberInt":"19"}}
{"_id":{"$oid":"63452ade10ab555e6021a390"},"id":{"$numberInt":"20"},"problem":{"$numberInt":"180"},"description":"Solved by using Javascript Functions","userId":{"$numberInt":"20"}}
{"_id":{"$oid":"63452ade10ab555e6021a391"},"id":{"$numberInt":"21"},"problem":{"$numberInt":"140"},"description":"Solved by using Mysql Introduction","userId":{"$numberInt":"21"}}
{"_id":{"$oid":"63452ade10ab555e6021a392"},"id":{"$numberInt":"22"},"problem":{"$numberInt":"230"},"description":"Solved by using Javascript Promises","userId":{"$numberInt":"22"}}
{"_id":{"$oid":"63452ade10ab555e6021a393"},"id":{"$numberInt":"23"},"problem":{"$numberInt":"190"},"description":"Solved by using React Context API","userId":{"$numberInt":"23"}}
{"_id":{"$oid":"63452ade10ab555e6021a394"},"id":{"$numberInt":"24"},"problem":{"$numberInt":"290"},"description":"Solved by using React Router","userId":{"$numberInt":"24"}}
{"_id":{"$oid":"63452ade10ab555e6021a395"},"id":{"$numberInt":"25"},"problem":{"$numberInt":"220"},"description":"Solved by using Javascript Callback Functions","userId":{"$numberInt":"25"}}
{"_id":{"$oid":"63452ade10ab555e6021a396"},"id":{"$numberInt":"26"},"problem":{"$numberInt":"260"},"description":"Solved by using HTML and CSS","userId":{"$numberInt":"26"}}
{"_id":{"$oid":"63452ade10ab555e6021a397"},"id":{"$numberInt":"27"},"problem":{"$numberInt":"240"},"description":"Solved by using Node JS","userId":{"$numberInt":"27"}}
{"_id":{"$oid":"63452ade10ab555e6021a398"},"id":{"$numberInt":"28"},"problem":{"$numberInt":"280"},"description":"Solved by using React DOM","userId":{"$numberInt":"28"}}
{"_id":{"$oid":"63452ade10ab555e6021a399"},"id":{"$numberInt":"29"},"problem":{"$numberInt":"250"},"description":"Solved by using Javascript Async Programming","userId":{"$numberInt":"29"}}
{"_id":{"$oid":"63452ade10ab555e6021a39a"},"id":{"$numberInt":"30"},"problem":{"$numberInt":"270"},"description":"Solved by using MongoDB","userId":{"$numberInt":"30"}}