{"_id":{"$oid":"6347f29410ab555e6021a5dd"},"id":{"$numberInt":"1"},"topicName":"React","month":"October","userId":{"$numberInt":"4"}}
{"_id":{"$oid":"6347f29410ab555e6021a5de"},"id":{"$numberInt":"2"},"topicName":"Node JS","month":"November","userId":{"$numberInt":"27"}}
{"_id":{"$oid":"6347f29410ab555e6021a5df"},"id":{"$numberInt":"3"},"topicName":"React Router","Date":"November","userId":{"$numberInt":"1"}}
{"_id":{"$oid":"6347f29410ab555e6021a5e0"},"id":{"$numberInt":"4"},"topicName":"Node Js Intro","month":"November","userId":{"$numberInt":"2"}}
{"_id":{"$oid":"6347f29410ab555e6021a5e1"},"id":{"$numberInt":"5"},"topicName":"Javascript","month":"October","userId":{"$numberInt":"16"}}
{"_id":{"$oid":"6347f29410ab555e6021a5e2"},"id":{"$numberInt":"6"},"topicName":"React Formik","month":"November","userId":{"$numberInt":"3"}}
{"_id":{"$oid":"6347f29410ab555e6021a5e3"},"id":{"$numberInt":"7"},"topicName":"HTML and CSS","month":"November","userId":{"$numberInt":"26"}}
{"_id":{"$oid":"6347f29410ab555e6021a5e4"},"id":{"$numberInt":"8"},"topicName":"Javascript Functions","month":"October","userId":{"$numberInt":"20"}}
{"_id":{"$oid":"6347f29410ab555e6021a5e5"},"id":{"$numberInt":"9"},"topicName":"MYSQL Intro","month":"October","userId":{"$numberInt":"21"}}
{"_id":{"$oid":"6347f29410ab555e6021a5e6"},"id":{"$numberInt":"10"},"topicName":"MongoDB","month":"November","userId":{"$numberInt":"10"}}
{"_id":{"$oid":"6347f29410ab555e6021a5e7"},"id":{"$numberInt":"11"},"topicName":"React Components","month":"October","userId":{"$numberInt":"18"}}
{"_id":{"$oid":"6347f29410ab555e6021a5e8"},"id":{"$numberInt":"12"},"topicName":"React Context API","month":"November","userId":{"$numberInt":"13"}}
{"_id":{"$oid":"6347f29410ab555e6021a5e9"},"id":{"$numberInt":"13"},"topicName":"Javascript Promises","month":"October","userId":{"$numberInt":"12"}}
{"_id":{"$oid":"6347f29410ab555e6021a5ea"},"id":{"$numberInt":"14"},"topicName":"Javascript Async and Await","month":"November","userId":{"$numberInt":"7"}}
{"_id":{"$oid":"6347f29410ab555e6021a5eb"},"id":{"$numberInt":"15"},"topicName":"React Hooks and States","month":"October","userId":{"$numberInt":"17"}}
{"_id":{"$oid":"6347f29410ab555e6021a5ec"},"id":{"$numberInt":"16"},"topicName":"React Hook useRef and useReducer","month":"October","userId":{"$numberInt":"25"}}
{"_id":{"$oid":"6347f29410ab555e6021a5ed"},"id":{"$numberInt":"17"},"topicName":"Javascript Async programming","month":"October","userId":{"$numberInt":"29"}}
{"_id":{"$oid":"6347f29410ab555e6021a5ee"},"id":{"$numberInt":"18"},"topicName":"React DOM","month":"October","userId":{"$numberInt":"28"}}
{"_id":{"$oid":"6347f29410ab555e6021a5ef"},"id":{"$numberInt":"19"},"topicName":"React ES5 vs ES6","month":"October","userId":{"$numberInt":"5"}}
{"_id":{"$oid":"6347f29410ab555e6021a5f0"},"id":{"$numberInt":"20"},"topicName":"Javascript Callback Function","month":"October","userId":{"$numberInt":"9"}}
{"_id":{"$oid":"6347f29410ab555e6021a5f1"},"id":{"$numberInt":"21"},"topicName":"Node JS and Express JS","month":"October","userId":{"$numberInt":"24"}}
{"_id":{"$oid":"6347f29410ab555e6021a5f2"},"id":{"$numberInt":"22"},"topicName":"Node and MongoDB connectivity","month":"November","userId":{"$numberInt":"15"}}
{"_id":{"$oid":"6347f29410ab555e6021a5f3"},"id":{"$numberInt":"23"},"topicName":"React Hooks","month":"October","userId":{"$numberInt":"8"}}
{"_id":{"$oid":"6347f29410ab555e6021a5f4"},"id":{"$numberInt":"24"},"topicName":"Javascript Browser and Web","month":"October","userId":{"$numberInt":"30"}}
{"_id":{"$oid":"6347f29410ab555e6021a5f5"},"id":{"$numberInt":"25"},"topicName":"Javascript Request and Response cycle","month":"October","userId":{"$numberInt":"6"}}
{"_id":{"$oid":"6347f29410ab555e6021a5f6"},"id":{"$numberInt":"26"},"topicName":"Javascript Arrays and Objects","month":"October","userId":{"$numberInt":"23"}}
{"_id":{"$oid":"6347f29410ab555e6021a5f7"},"id":{"$numberInt":"27"},"topicName":"Oops in Javascript","month":"October","userId":{"$numberInt":"22"}}
{"_id":{"$oid":"6347f29410ab555e6021a5f8"},"id":{"$numberInt":"28"},"topicName":"Promise Request Info & Request Init","month":"October","userId":{"$numberInt":"14"}}
{"_id":{"$oid":"6347f29410ab555e6021a5f9"},"id":{"$numberInt":"29"},"topicName":"HTML and CSS Responsive Web Design","month":"October","userId":{"$numberInt":"19"}}
{"_id":{"$oid":"6347f29410ab555e6021a5fa"},"id":{"$numberInt":"30"},"topicName":"React with CRUD","month":"October","userId":{"$numberInt":"11"}}